{
  "detection": {
    "base_confidence": 0.3,
    "iou_threshold": 0.4,
    "max_detections": 50,
    "class_thresholds": {
      "8": 0.4,
      "37": 0.5,
      "0": 0.8,
      "1": 0.9,
      "2": 0.9,
      "3": 0.9,
      "32": 0.9,
      "29": 0.9,
      "33": 0.9
    },
    "use_multi_pass": false,
    "confidence_levels": [0.3, 0.5]
  },

  "geometry": {
    "min_width": 80,
    "max_width": 800,
    "min_height": 20,
    "max_height": 200,
    "min_area": 2000,
    "max_area": 80000,
    "min_aspect_ratio": 3.0,
    "max_aspect_ratio": 15.0,
    "preferred_ratio_min": 4.0,
    "preferred_ratio_max": 12.0,
    "size_weight": 0.3,
    "aspect_weight": 0.4,
    "orientation_weight": 0.2,
    "class_weight": 0.1
  },

  "canoe_scoring": {
    "min_canoe_score": 0.6,
    "boat_bonus": 0.8,
    "surfboard_bonus": 0.6,
    "horizontal_bonus": 0.4,
    "size_bonus_range": [3000, 40000],
    "aspect_bonus_range": [4.0, 10.0]
  },

  "adaptive": {
    "enabled": false,
    "learning_rate": 0.005,
    "false_positive_penalty": 0.1,
    "true_positive_reward": 0.01,
    "adaptation_window": 200
  },

  "tracking": {
    "max_distance": 150,
    "max_age": 20,
    "min_confidence": 0.4,
    "prediction_enabled": true,
    "occlusion_tolerance": 5
  },

  "visualization": {
    "show_all_scores": true,
    "show_detection_type": true,
    "color_by_confidence": true,
    "trajectory_length": 30,
    "show_rejected": false
  }
}
